{"cameraMode":{"drawMode":0,"name":"Shaded","section":"Shading Mode"},"sceneLighting":false,"audioPlay":false,"sceneViewState":{"showFog":true,"showMaterialUpdate":false,"showSkybox":false,"showFlares":true,"showImageEffects":true,"showParticleSystems":true},"in2DMode":false,"pivot":{"x":26.394126892089845,"y":1.652500033378601,"z":-7.747750282287598},"rotation":{"x":0.3930590748786926,"y":-0.07298606634140015,"z":0.0313163585960865,"w":0.9160788655281067},"size":1.2471016645431519,"orthographic":false}